sol239_serialization/__init__.py
sol239_serialization/serialization.py
sol239_serialization-0.2.3.dist-info/LICENSE
sol239_serialization-0.2.3.dist-info/METADATA
sol239_serialization-0.2.3.dist-info/WHEEL
sol239_serialization-0.2.3.dist-info/top_level.txt
sol239_serialization-0.2.3.dist-info/RECORD
