Metadata-Version: 2.1
Name: sol239_serialization
Version: 0.2.3
Summary: A package for serializing and deserializing data
Home-page: https://github.com/sol239/ClassSerialization
Author: sol239
Author-email: 239sol239@gmail.com
License: GPLv3
Classifier: Programming Language :: Python :: 3
Classifier: License :: OSI Approved :: GNU General Public License v3 (GPLv3)
Classifier: Operating System :: OS Independent
Requires-Python: >=3.6
License-File: LICENSE
